<?xml version="1.0" encoding="UTF-8"?>
<objects serializationModel="Studio.02.02.00">
	<object class="AudioFile" id="{1e232af5-7953-4020-a5a3-16f3f722d5a8}">
		<property name="assetPath">
			<value>enemy_boss_bouncer_movement1.mp3</value>
		</property>
		<property name="frequencyInKHz">
			<value>44.0999985</value>
		</property>
		<property name="channelCount">
			<value>2</value>
		</property>
		<property name="length">
			<value>1.0971428571428572</value>
		</property>
		<relationship name="masterAssetFolder">
			<destination>{469de9f7-7cb3-4f67-a797-a630185fa14d}</destination>
		</relationship>
	</object>
</objects>
